README.txt
setup.py
ilp/__init__.py
ilp/index.py
ilp.egg-info/PKG-INFO
ilp.egg-info/SOURCES.txt
ilp.egg-info/dependency_links.txt
ilp.egg-info/entry_points.txt
ilp.egg-info/requires.txt
ilp.egg-info/top_level.txt
ilp/cmdline/__init__.py
ilp/database/__init__.py
ilp/database/_api.py
ilp/database/_shelvedb.py
ilp/utils/__init__.py
ilp/utils/file.py
ilp/utils/funcmap.py
ilp/utils/funcset.py
ilp/utils/functuple.py