Metadata-Version: 1.1
Name: ilp
Version: 0.2
Summary: a tag-based file indexer
Home-page: https://github.com/slowpoketail/ilp
Author: slowpoke
Author-email: mail+python at slowpoke dot io
License: ANTI-LICENSE
Platform: UNKNOWN
Classifier: Environment :: Console
Classifier: Development Status :: 4 - Beta
Classifier: License :: Public Domain
Classifier: Programming Language :: Python :: 3
